mlcomposer/__init__.py
mlcomposer/trainer.py
mlcomposer/transformers.py
mlcomposer-0.1.1.dist-info/LICENSE
mlcomposer-0.1.1.dist-info/METADATA
mlcomposer-0.1.1.dist-info/WHEEL
mlcomposer-0.1.1.dist-info/top_level.txt
mlcomposer-0.1.1.dist-info/RECORD
