Metadata-Version: 2.1
Name: mlcomposer
Version: 0.1.1
Summary: Treinamento e avaliação de modelos de machine learning através de funções e classes encapsuladas
Home-page: https://github.com/ThiagoPanini/mlcomposer
Author: Thiago Panini
Author-email: thipanini94@gmail.com
License: MIT
Keywords: Packages,Components,Machine Learning,Auto ML,Viz
Platform: UNKNOWN
Classifier: Programming Language :: Python :: 3
Classifier: Development Status :: 3 - Alpha
Classifier: Environment :: Console
Classifier: Framework :: Jupyter
Classifier: Intended Audience :: Developers
Classifier: Natural Language :: Portuguese (Brazilian)
Classifier: License :: OSI Approved :: MIT License
Classifier: Operating System :: OS Independent
Classifier: Programming Language :: Python :: 3.6
Classifier: Programming Language :: Python :: 3.7
Classifier: Programming Language :: Python :: 3.8
Classifier: Programming Language :: Python :: 3.9
Classifier: Topic :: Software Development :: Libraries :: Python Modules
Requires-Python: >=3.0.0
Requires-Dist: joblib
Requires-Dist: matplotlib
Requires-Dist: numpy
Requires-Dist: pandas
Requires-Dist: python-dotenv (==0.17.0)
Requires-Dist: scikit-learn
Requires-Dist: seaborn
Requires-Dist: shap (==0.37.0)
